odoo8_addon_account_invoice_pricelist_stock_account-8.0.1.0.0.99.dev2-py2.7-nspkg.pth
odoo8_addon_account_invoice_pricelist_stock_account-8.0.1.0.0.99.dev2.dist-info/METADATA
odoo8_addon_account_invoice_pricelist_stock_account-8.0.1.0.0.99.dev2.dist-info/RECORD
odoo8_addon_account_invoice_pricelist_stock_account-8.0.1.0.0.99.dev2.dist-info/WHEEL
odoo8_addon_account_invoice_pricelist_stock_account-8.0.1.0.0.99.dev2.dist-info/namespace_packages.txt
odoo8_addon_account_invoice_pricelist_stock_account-8.0.1.0.0.99.dev2.dist-info/top_level.txt
odoo_addons/account_invoice_pricelist_stock_account/README.rst
odoo_addons/account_invoice_pricelist_stock_account/__init__.py
odoo_addons/account_invoice_pricelist_stock_account/__openerp__.py
odoo_addons/account_invoice_pricelist_stock_account/models/__init__.py
odoo_addons/account_invoice_pricelist_stock_account/models/stock_picking.py
odoo_addons/account_invoice_pricelist_stock_account/static/description/icon.png
