Metadata-Version: 2.1
Name: odoo8-addon-account-invoice-pricelist-stock-account
Version: 8.0.1.0.0.99.dev2
Summary: Set pricelist from SO / PO in invoice created from picking
Home-page: http://github.com/OCA/account-invoicing
Author: Therp BV,GRAP,Odoo Community Association (OCA)
Author-email: support@odoo-community.org
License: AGPL-3
Platform: UNKNOWN
Classifier: Programming Language :: Python
Classifier: Framework :: Odoo
Classifier: License :: OSI Approved :: GNU Affero General Public License v3
Requires-Python: ~=2.7
Requires-Dist: odoo8-addon-account-invoice-pricelist
Requires-Dist: odoo (<9.0a,>=8.0a)
